autodiscovery/__init__.py
autodiscovery-0.0.2.dist-info/LICENSE
autodiscovery-0.0.2.dist-info/METADATA
autodiscovery-0.0.2.dist-info/WHEEL
autodiscovery-0.0.2.dist-info/top_level.txt
autodiscovery-0.0.2.dist-info/RECORD
