Metadata-Version: 2.1
Name: autodiscovery
Version: 0.0.2
Summary: autodiscovery is a Python library that simplifies the discovery of Python applications on a network, allowing seamless connection and interaction between services with minimal configuration.
Home-page: https://github.com/Michael-Jalloh/Autodiscovery
Author: Michael Jalloh
Author-email: michaeljalloh19@gmail.com
License: MIT
Project-URL: issues, https://github.com/Michael-Jalloh/Autodiscovery/issues
Project-URL: source, https://github.com/Michael-Jalloh/Autodiscovery
Platform: any
Classifier: Development Status :: 4 - Beta
Classifier: Intended Audience :: Developers
Classifier: Topic :: Software Development :: Build Tools
Classifier: License :: OSI Approved :: MIT License
Classifier: Programming Language :: Python :: 3.7
Classifier: Programming Language :: Python :: 3.8
Classifier: Programming Language :: Python :: 3.9
Classifier: Programming Language :: Python :: 3.10
Classifier: Programming Language :: Python :: 3.11
Classifier: Programming Language :: Python :: 3.12
License-File: LICENSE
